operator_precedence_high_roller_bot/high_roller.py
operator_precedence_high_roller_bot/message_validator.py
operator_precedence_high_roller_bot/computing/__init__.py
operator_precedence_high_roller_bot/computing/compute.py
operator_precedence_high_roller_bot/json_handling/__init__.py
operator_precedence_high_roller_bot/json_handling/json_handle.py
operator_precedence_high_roller_bot/json_handling/gambling/__init__.py
operator_precedence_high_roller_bot/json_handling/gambling/gamble.py
operator_precedence_high_roller_bot/json_handling/roll_saving/__init__.py
operator_precedence_high_roller_bot/json_handling/roll_saving/roll_save.py
operator_precedence_high_roller_bot/parsing/__init__.py
operator_precedence_high_roller_bot/parsing/command_parser.py
operator_precedence_high_roller_bot/parsing/command_token.py
operator_precedence_high_roller_bot/parsing/input_buffer.py
operator_precedence_high_roller_bot/parsing/lexical_analyzer.py
operator_precedence_high_roller_bot/parsing/stacknode.py
operator_precedence_high_roller_bot/parsing/enums/__init__.py
operator_precedence_high_roller_bot/parsing/enums/command_type.py
operator_precedence_high_roller_bot/parsing/enums/token_type.py
operator_precedence_high_roller_bot-1.1.1.dist-info/METADATA
operator_precedence_high_roller_bot-1.1.1.dist-info/WHEEL
operator_precedence_high_roller_bot-1.1.1.dist-info/licenses/LICENSE
operator_precedence_high_roller_bot-1.1.1.dist-info/RECORD
