Metadata-Version: 2.3
Name: operator_precedence_high_roller_bot
Version: 1.1.1
Summary: A small example package
Project-URL: Homepage, https://github.com/carsonrobertsg2019/operator-precedence-high-roller
Author-email: Jade Roberts <jaderobertsg2019@gmail.com>
License-File: LICENSE
Classifier: License :: OSI Approved :: MIT License
Classifier: Operating System :: OS Independent
Classifier: Programming Language :: Python :: 3
Requires-Python: >=3.11
